{
  "main": {
    "id": "bc75f61d55cc2a3c",
    "type": "split",
    "children": [
      {
        "id": "d36ea942add94d1a",
        "type": "tabs",
        "children": [
          {
            "id": "e2fe7dd7d3d94d94",
            "type": "leaf",
            "state": {
              "type": "markdown",
              "state": {
                "file": "Unit 1/2025-10-21 - Contemporary Approaches.md",
                "mode": "preview",
                "source": false
              },
              "icon": "lucide-file",
              "title": "2025-10-21 - Contemporary Approaches"
            }
          },
          {
            "id": "a0c49c71a4a2c831",
            "type": "leaf",
            "state": {
              "type": "markdown",
              "state": {
                "file": "Unit 2/Strategic Management.md",
                "mode": "source",
                "source": false
              },
              "icon": "lucide-file",
              "title": "Strategic Management"
            }
          }
        ],
        "currentTab": 1
      }
    ],
    "direction": "vertical"
  },
  "left": {
    "id": "1a4186f86c03b1a6",
    "type": "mobile-drawer",
    "children": [
      {
        "id": "4c71d184aece94cc",
        "type": "leaf",
        "state": {
          "type": "file-explorer",
          "state": {
            "sortOrder": "alphabetical",
            "autoReveal": false
          },
          "icon": "lucide-folder-closed",
          "title": "Files"
        }
      },
      {
        "id": "e76e267dcfed7934",
        "type": "leaf",
        "state": {
          "type": "search",
          "state": {
            "query": "",
            "matchingCase": false,
            "explainSearch": false,
            "collapseAll": false,
            "extraContext": false,
            "sortOrder": "alphabetical"
          },
          "icon": "lucide-search",
          "title": "Search"
        }
      },
      {
        "id": "2150b95ff5fe878d",
        "type": "leaf",
        "state": {
          "type": "tag",
          "state": {
            "sortOrder": "frequency",
            "useHierarchy": true,
            "showSearch": false,
            "searchQuery": ""
          },
          "icon": "lucide-tags",
          "title": "Tags"
        }
      },
      {
        "id": "a0a0f297375a2ed3",
        "type": "leaf",
        "state": {
          "type": "bookmarks",
          "state": {},
          "icon": "lucide-bookmark",
          "title": "Bookmarks"
        }
      }
    ],
    "currentTab": 0
  },
  "right": {
    "id": "fe00ad2718d89357",
    "type": "mobile-drawer",
    "children": [
      {
        "id": "c907aa26b2a2afa6",
        "type": "leaf",
        "state": {
          "type": "backlink",
          "state": {
            "file": "Unit 1/2025-10-21 - Contemporary Approaches.md",
            "collapseAll": false,
            "extraContext": false,
            "sortOrder": "alphabetical",
            "showSearch": false,
            "searchQuery": "",
            "backlinkCollapsed": false,
            "unlinkedCollapsed": true
          },
          "icon": "links-coming-in",
          "title": "Backlinks"
        }
      },
      {
        "id": "b2189eb49bee253d",
        "type": "leaf",
        "state": {
          "type": "outgoing-link",
          "state": {
            "file": "2025-10-08 - Intro to management and organization.md",
            "linksCollapsed": false,
            "unlinkedCollapsed": true
          },
          "icon": "links-going-out",
          "title": "Outgoing links"
        }
      },
      {
        "id": "47b3f35a57da5dc9",
        "type": "leaf",
        "state": {
          "type": "outline",
          "state": {
            "file": "2025-10-08 - Intro to management and organization.md",
            "followCursor": false,
            "showSearch": false,
            "searchQuery": ""
          },
          "icon": "lucide-list",
          "title": "Outline"
        }
      }
    ],
    "currentTab": 0
  },
  "left-ribbon": {
    "hiddenItems": {
      "switcher:Open quick switcher": false,
      "graph:Open graph view": false,
      "canvas:Create new canvas": false,
      "daily-notes:Open today's daily note": false,
      "templates:Insert template": false,
      "command-palette:Open command palette": false,
      "bases:Create new base": false
    }
  },
  "active": "a0c49c71a4a2c831",
  "lastOpenFiles": [
    "CIEs.md",
    "Unit 2/Strategic Management.md",
    "Unit 4/2025-11-03 - Economics.md",
    "Untitled.md",
    "Unit 1/2025-10-21 - Contemporary Approaches.md",
    "Unit 1/2025-10-21 - Operations Research.md",
    "Unit 1/2025-10-13 - Evolution of Management thought.md",
    "Unit 4/2025-11-05 - Types of Economics Systems.md",
    "2025-10-29.md",
    "Unit 4/2025-11-03 - Micro and Macro Economics.md",
    "Ppt/01 MOB - Introduction to Management.pdf",
    "images/Circular-Flow-Model-1-590226cd3df78c5456a6ddf4.jpg",
    "Unit 1/2025-10-08 - POSDCORB.md",
    "Unit 1/2025-10-08 - Intro to management and organization.md",
    "Unit 4/2025-11-05 - Circular Flow Model.md",
    "Unit 1/Hawthorne Studies.md",
    "Unit 1/2025-10-27 - Comparision.md",
    "images/model_of_system_theory_for_organization_management_slide01.jpg",
    "images",
    "Unit 2/Planning.md",
    "Unit 4",
    "Unit 2",
    "Ppt",
    "Unit 1",
    "2025-10-08.md",
    "Ppt/02A MOB - Foundations of Planning.pdf"
  ]
}